tarix/__init__.py
tarix/clac.py
tarix/date.py
tarix-0.1.1.dist-info/LICENSE.txt
tarix-0.1.1.dist-info/METADATA
tarix-0.1.1.dist-info/WHEEL
tarix-0.1.1.dist-info/RECORD
